Metadata-Version: 2.1
Name: odoo14-addon-base-rest-datamodel
Version: 14.0.4.3.0
Summary: Datamodel binding for base_rest
Home-page: https://github.com/OCA/rest-framework
Author: ACSONE SA/NV,Odoo Community Association (OCA)
Author-email: support@odoo-community.org
License: LGPL-3
Platform: UNKNOWN
Classifier: Programming Language :: Python
Classifier: Framework :: Odoo
Classifier: Framework :: Odoo :: 14.0
Classifier: License :: OSI Approved :: GNU Lesser General Public License v3 (LGPLv3)
Requires-Python: >=3.6
Requires-Dist: apispec
Requires-Dist: marshmallow
Requires-Dist: odoo14-addon-base-rest
Requires-Dist: odoo14-addon-datamodel
Requires-Dist: odoo (<14.1dev,>=14.0a)
